datanommer/models/__init__.py
datanommer/models/alembic/env.py
datanommer/models/alembic/script.py.mako
datanommer/models/alembic/versions/429e6f2cba6f_message_agent_name.py
datanommer/models/alembic/versions/5db25abc63be_init.py
datanommer/models/alembic/versions/951c40020acc_unique.py
datanommer/models/alembic/versions/f4fdb5442d05_add_view_recent_topics.py
datanommer/models/alembic/versions/f6918385051f_messages_headers_index.py
datanommer/models/testing/__init__.py
datanommer/models/view.py
datanommer_models-1.5.0.dist-info/METADATA
datanommer_models-1.5.0.dist-info/WHEEL
datanommer_models-1.5.0.dist-info/licenses/LICENSE
datanommer_models-1.5.0.dist-info/RECORD
